qoptcraft/__init__.py
qoptcraft/_version.py
qoptcraft/config.py
qoptcraft/_legacy/__init__.py
qoptcraft/_legacy/input_control.py
qoptcraft/_legacy/mat_inner_product.py
qoptcraft/_legacy/optic_devices.py
qoptcraft/_legacy/photon_comb_basis.py
qoptcraft/_legacy/read_matrix.py
qoptcraft/_legacy/recur_factorial.py
qoptcraft/_legacy/unitary.py
qoptcraft/_legacy/write_initial_matrix.py
qoptcraft/_legacy/Main_Code/_0_FullAlgorithm.py
qoptcraft/_legacy/Main_Code/_1_Unitary_matrix_U_builder.py
qoptcraft/_legacy/Main_Code/_2_Get_U_matrix_of_photon_system_evolution.py
qoptcraft/_legacy/Main_Code/_2_aux_a_computation_time_evolutions_comparison.py
qoptcraft/_legacy/Main_Code/_2_aux_b_logarithm_algorithms_equalities.py
qoptcraft/_legacy/Main_Code/_2_aux_c_logarithm_algorithms_timesanderror.py
qoptcraft/_legacy/Main_Code/_3_Get_S_from_U_Inverse_problem.py
qoptcraft/_legacy/Main_Code/_4_toponogov_theorem_for_uncraftable_matrices_U.py
qoptcraft/_legacy/Main_Code/_5_Quasiunitary_S_with_or_without_loss_builder.py
qoptcraft/_legacy/Main_Code/_6_schmidt_entanglement_measurement_of_states.py
qoptcraft/_legacy/Main_Code/_7_generators.py
qoptcraft/_legacy/Main_Code/_9_friendly_logarithm_algorithms.py
qoptcraft/_legacy/Main_Code/__init__.py
qoptcraft/_legacy/Phase1_Aux/Tmn.py
qoptcraft/_legacy/Phase1_Aux/_1_U_decomposition.py
qoptcraft/_legacy/Phase1_Aux/_1_U_decomposition_Reck.py
qoptcraft/_legacy/Phase1_Aux/_1_U_recomposition.py
qoptcraft/_legacy/Phase1_Aux/_1_U_recomposition_Reck.py
qoptcraft/_legacy/Phase1_Aux/__init__.py
qoptcraft/_legacy/Phase2_Aux/_2_1st_evolution_method.py
qoptcraft/_legacy/Phase2_Aux/_2_2nd_evolution_method.py
qoptcraft/_legacy/Phase2_Aux/_2_3rd_evolution_method.py
qoptcraft/_legacy/Phase2_Aux/_2_creation_and_destruction_operators.py
qoptcraft/_legacy/Phase2_Aux/_2_logarithm_algorithms.py
qoptcraft/_legacy/Phase2_Aux/_2_photon_input.py
qoptcraft/_legacy/Phase2_Aux/__init__.py
qoptcraft/_legacy/Phase2_Aux/ryser_permanent.py
qoptcraft-2.0.0.dist-info/LICENSE
qoptcraft-2.0.0.dist-info/METADATA
qoptcraft-2.0.0.dist-info/WHEEL
qoptcraft-2.0.0.dist-info/top_level.txt
qoptcraft-2.0.0.dist-info/RECORD
