Metadata-Version: 2.1
Name: qoptcraft
Version: 2.0.0
Summary: A package for the design and study of linear optical quantum systems.
Author-email: Daniel Gómez Aguado <gomezaguado99@gmail.com>, "Pablo V. Parellada" <pablo.veganzones@uva.es>
Maintainer-email: "Pablo V. Parellada" <pablo.veganzones@uva.es>
License: Apache License
Project-URL: repository, https://gitlab.tel.uva.es/juagar/qoptcraft
Platform: unix
Platform: linux
Platform: osx
Platform: cygwin
Platform: win32
Classifier: Programming Language :: Python :: 3
Classifier: Programming Language :: Python :: 3.10
Classifier: Programming Language :: Python :: 3.11
Classifier: Operating System :: Microsoft :: Windows
Classifier: Operating System :: POSIX :: Linux
Classifier: Operating System :: POSIX
Classifier: Operating System :: Unix
Classifier: Operating System :: MacOS
Requires-Python: >=3.10
License-File: LICENSE
Requires-Dist: numpy
Requires-Dist: scipy
Requires-Dist: numba
Requires-Dist: sympy
Provides-Extra: build
Requires-Dist: setuptools ; extra == 'build'
Requires-Dist: build ; extra == 'build'
Requires-Dist: twine ; extra == 'build'
Provides-Extra: dev
Requires-Dist: qoptcraft[build,docs,lint,test] ; extra == 'dev'
Provides-Extra: docs
Requires-Dist: mkdocs ; extra == 'docs'
Requires-Dist: mkdocstrings ; extra == 'docs'
Requires-Dist: mkdocstrings[python] ; extra == 'docs'
Requires-Dist: mkdocs-material ; extra == 'docs'
Requires-Dist: Pygments ; extra == 'docs'
Requires-Dist: python-markdown-math ; extra == 'docs'
Requires-Dist: mkdocs-gen-files ; extra == 'docs'
Requires-Dist: mkdocs-literate-nav ; extra == 'docs'
Requires-Dist: mkdocs-section-index ; extra == 'docs'
Requires-Dist: mkdocs-same-dir ; extra == 'docs'
Requires-Dist: mkdocs-autorefs ; extra == 'docs'
Requires-Dist: mkdocs-jupyter ; extra == 'docs'
Provides-Extra: lint
Requires-Dist: ruff ; extra == 'lint'
Requires-Dist: black ; extra == 'lint'
Requires-Dist: black[jupyter] ; extra == 'lint'
Requires-Dist: mypy ; extra == 'lint'
Requires-Dist: vulture ; extra == 'lint'
Provides-Extra: test
Requires-Dist: pytest ; extra == 'test'
Requires-Dist: pyinstrument ; extra == 'test'
Requires-Dist: hypothesis ; extra == 'test'
